xl2times/__init__.py
xl2times/__main__.py
xl2times/datatypes.py
xl2times/dd_to_csv.py
xl2times/excel.py
xl2times/main.py
xl2times/transforms.py
xl2times/utils.py
xl2times/config/__init__.py
xl2times/config/times-info.json
xl2times/config/times-sets.json
xl2times/config/times_mapping.txt
xl2times/config/veda-attr-defaults.json
xl2times/config/veda-tags.json
xl2times/gams_scaffold/__init__.py
xl2times/gams_scaffold/gams.opt
xl2times/gams_scaffold/runmodel.gms
xl2times/gams_scaffold/scenario.run
xl2times-0.3.0.dist-info/licenses/AUTHORS.md
xl2times-0.3.0.dist-info/licenses/LICENSE
xl2times-0.3.0.dist-info/METADATA
xl2times-0.3.0.dist-info/WHEEL
xl2times-0.3.0.dist-info/entry_points.txt
xl2times-0.3.0.dist-info/top_level.txt
xl2times-0.3.0.dist-info/RECORD
