Metadata-Version: 2.4
Name: xl2times
Version: 0.3.0
Summary: An open source tool to convert TIMES models specified in Excel to a format ready for processing by GAMS
Author-email: Sam Webster <13457618+samwebster@users.noreply.github.com>, Tom Minka <8955276+tminka@users.noreply.github.com>, Siddharth Krishna <siddharth-krishna@users.noreply.github.com>, Olexandr Balyk <ob@facilitate.energy>
Maintainer-email: Siddharth Krishna <siddharth-krishna@users.noreply.github.com>, Olexandr Balyk <ob@facilitate.energy>
License: MIT License
Project-URL: Documentation, https://xl2times.readthedocs.io
Project-URL: Issues, https://github.com/etsap-TIMES/xl2times/issues
Project-URL: Source, https://github.com/etsap-TIMES/xl2times
Classifier: Development Status :: 4 - Beta
Classifier: License :: OSI Approved :: MIT License
Classifier: Programming Language :: Python
Classifier: Programming Language :: Python :: 3
Requires-Python: >=3.11
License-File: LICENSE
License-File: AUTHORS.md
Requires-Dist: GitPython<3.2,>=3.1.31
Requires-Dist: more-itertools
Requires-Dist: openpyxl>=3.1.3
Requires-Dist: pandas>=2.1
Requires-Dist: pyarrow
Requires-Dist: tqdm
Requires-Dist: loguru
Provides-Extra: dev
Requires-Dist: black; extra == "dev"
Requires-Dist: gamspy-base; extra == "dev"
Requires-Dist: pre-commit; extra == "dev"
Requires-Dist: tabulate; extra == "dev"
Requires-Dist: pytest; extra == "dev"
Requires-Dist: pytest-cov; extra == "dev"
Requires-Dist: poethepoet; extra == "dev"
Requires-Dist: ruff; extra == "dev"
Dynamic: license-file
